{
  "doctor": [
    {
      "id": 1,
      "doctor_name": "นันทชัย ",
      "docter_phonenumber": "888888888",
      "department_id ": "1"
    },
    {
      "id": 2,
      "doctor_name": "ณรงค์ฤทธิ์ ",
      "docter_phonenumber": "0954515454",
      "department_id ": "2"
    },
    {
      "id": 3,
      "doctor_name": "ศิวกร ",
      "docter_phonenumber": "0987456123",
      "department_id ": "3"
    },
    {
      "id": 4,
      "doctor_name": "เอิท ",
      "docter_phonenumber": "0989751542",
      "department_id ": "3"
    }
  ],
  "hospital": [
    {
      "id": 1,
      "hospital_name": "โรงพยาบาลสมเด็จพระสังฆราช องค์ที่ 17 ",
      "hospital_logo": "https://rsathai.org/wp-content/uploads/2018/09/download-10-1.jpg",
      "hospital_phone_number ": "1150",
      "hospital_No ": "88",
      "hospital_Moo ": "12",
      "hospital_subdistrict ": "Noenpraprang",
      "hospital_district ": "Song Phi Nong",
      "hospital_province ": "SuphanBuri",
      "hospital_zipcode ": "72110"
    },
    {
      "id": 2,
      "hospital_name": "โรงพยาบาลสมเด็จพระสังฆราช องค์ที่ 18 ",
      "hospital_logo": "https://rsathai.org/wp-content/uploads/2018/09/download-10-1.jpg",
      "hospital_phone_number ": "1150",
      "hospital_No ": "88",
      "hospital_Moo ": "12",
      "hospital_subdistrict ": "Noenpraprang",
      "hospital_district ": "Song Phi Nong",
      "hospital_province ": "SuphanBuri",
      "hospital_zipcode ": "72110"
    },
    {
      "id": 3,
      "hospital_name": "โรงพยาบาลสมเด็จพระสังฆราช องค์ที่ 19 ",
      "hospital_logo": "https://rsathai.org/wp-content/uploads/2018/09/download-10-1.jpg",
      "hospital_phone_number ": "1150",
      "hospital_No ": "88",
      "hospital_Moo ": "12",
      "hospital_subdistrict ": "Noenpraprang",
      "hospital_district ": "Song Phi Nong",
      "hospital_province ": "SuphanBuri",
      "hospital_zipcode ": "72110"
    },
    {
      "id": 4,
      "hospital_name": "โรงพยาบาลสมเด็จพระสังฆราช องค์ที่ 20 ",
      "hospital_logo": "https://rsathai.org/wp-content/uploads/2018/09/download-10-1.jpg",
      "hospital_phone_number ": "1150",
      "hospital_No ": "88",
      "hospital_Moo ": "12",
      "hospital_subdistrict ": "Noenpraprang",
      "hospital_district ": "Song Phi Nong",
      "hospital_province ": "SuphanBuri",
      "hospital_zipcode ": "72110"
    }
  ],
  "patient": [
    {
      "id": 1,
      "id_card": "1729800000099",
      "fistname": "ณรงค์ฤทธิ์",
      "lastname": "สุปรานนท์",
      "password": "",
      "birthday": "0000-00-00",
      "age": 22,
      "weight": 65,
      "height": 178,
      "nationality": "178",
      "religion": "พุทธ",
      "contact_person": "ศิวกร",
      "history_drug_allergy": "ไม่มี",
      "phone_number": "989999999"
    },
    {
      "id": 2,
      "id_card": "1729800000099",
      "fistname": "นันทชัย",
      "lastname": "แสงอรุณ",
      "password": "",
      "birthday": "0000-00-00",
      "age": 22,
      "weight": 65,
      "height": 178,
      "nationality": "178",
      "religion": "พุทธ",
      "contact_person": "ศิวกร",
      "history_drug_allergy": "ไม่มี",
      "phone_number": "989999999"
    },
    {
      "id": 3,
      "id_card": "1729800000002",
      "fistname": "นันทชัย",
      "lastname": "แสงอรุณ",
      "password": "",
      "birthday": "0000-00-00",
      "age": 22,
      "weight": 65,
      "height": 178,
      "nationality": "ไทย",
      "religion": "พุทธ",
      "contact_person": "ศิวกร",
      "history_drug_allergy": "ไม่มี",
      "phone_number": "989999999"
    }
  ],
  "questionaire": [
    {
      "id": 1,
      "questionaire_name": "ระบบควรปรับปรุงอย่างยิ่ง"
    },
    {
      "id": 2,
      "questionaire_name": "ระบบควรปรับปรุง"
    },
    {
      "id": 3,
      "questionaire_name": "ระบบใช้งานได้สะดวกพอใช้"
    },
    {
      "id": 4,
      "questionaire_name": "ระบบใช้งานได้สะดวกดี"
    },
    {
      "id": 5,
      "questionaire_name": "ระบบใช้งานได้สะดวกดีมาก"
    }
  ],
  "congenitalDisease": [
    {
      "id": 1,
      "cd_name": "โรคมะเร็ง",
      "symptom": "ระบบขับถ่ายผิดปกติ กลืนอาหารลำบาก"
    },
    {
      "id": 2,
      "cd_name": "โรคหัวใจ",
      "symptom": "เจ็บแน่นหน้าอก มักมีอาการแน่น อึดอัด หัวใจเต้นผิดจังหวะ เหนื่อยง่ายหายใจถี่"
    },
    {
      "id": 3,
      "cd_name": "โรคเบาหวาน",
      "symptom": "ปัสสาวะบ่อย โดยเฉพาะต้องตื่นมาปัสสาวะตอนกลางคืน ตาพร่ามัว ชาบริเวณปลายมือปลายเท้า"
    },
    {
      "id": 4,
      "cd_name": "โรคความดันโลหิตสูง",
      "symptom": "ปวดมึนท้ายทอย ตึงที่ต้นคอ เวียนศีรษะ บางรายอาจมีอาการปวดศีรษะตุบๆ เหมือนไมเกรน ในผู้ป่วยที่เป็นมานาน อาจมีอาการอ่อนเพลีย เหนื่อยง่าย ใจสั่น นอนไม่หลับ"
    },
    {
      "id": 5,
      "cd_name": "โรคภูมิแพ้",
      "symptom": "มีผื่นที่ผิวหนัง คัดจมูก น้ำมูกไหล จาม ไอ แน่นหน้าอก หายใจมีเสียงหวีด โรคหอบ หืด เคืองตา และตาแดง"
    }
  ],
  "queue": [
    {
      "id": 1,
      "queue_date": "15/03/2565",
      "create_at": "2023-03-16 05:54:30",
      "department_id": "1",
      "id_card": "1234567891236",
      "questionnaire_id": "1",
      "queue_status_id": "1",
      "authorities_id": "1"
    },
    {
      "id": 2,
      "queue_date": "17/03/2565",
      "create_at": "2023-03-16 16:54:30",
      "department_id": "1",
      "id_card": "987654321123",
      "questionnaire_id": "1",
      "queue_status_id": "1",
      "authorities_id": "1"
    }
  ],
  "havepatient": [
    {
      "id": 1,
      "id_card": "1234567891236",
      "cd_id": "1"
    },
    {
      "id": 2,
      "id_card": "987654321123",
      "cd_id": "2"
    }
  ],
  "department": [
    {
      "id": 1,
      "department_name": "ทันตกรรม",
      "department_image": "https://www.google.com/url?sa=i&url=https%3A%2F%2Fthaksinhospital.com%2Fthaksin%2Fdepartment_detail.php%3Fmenu%3D1%26id%3D2&psig=AOvVaw1gFo2WwZqOoJPLDIq5BJDl&ust=1678686478156000&source=images&cd=vfe&ved=0CA0QjRxqFwoTCLCmtc3Y1f0CFQAAAAAdAAAAABAD",
      "open_time": "10.00",
      "close_time": "16.00",
      "location": "165 ถ.บางลี่-หนองวัลย์เปรียง Song Phi Nong, Song Phi Nong District, Suphan Buri 72110",
      "building": "อาคาร1",
      "floor": "3",
      "max_queue_number": "200"
    },
    {
      "id": 2,
      "department_name": "ทันตกรรม",
      "department_image": "https://www.google.com/url?sa=i&url=https%3A%2F%2Fthaksinhospital.com%2Fthaksin%2Fdepartment_detail.php%3Fmenu%3D1%26id%3D2&psig=AOvVaw1gFo2WwZqOoJPLDIq5BJDl&ust=1678686478156000&source=images&cd=vfe&ved=0CA0QjRxqFwoTCLCmtc3Y1f0CFQAAAAAdAAAAABAD",
      "open_time": "10.00",
      "close_time": "16.00",
      "location": "165 ถ.บางลี่-หนองวัลย์เปรียง Song Phi Nong, Song Phi Nong District, Suphan Buri 72110",
      "building": "อาคาร2",
      "floor": "3",
      "max_queue_number": "200"
    },
    {
      "id": 3,
      "department_name": "แผนกสูติ-นรีเวช",
      "department_image": "https://www.google.com/url?sa=i&url=https%3A%2F%2Fthaksinhospital.com%2Fthaksin%2Fdepartment_detail.php%3Fmenu%3D1%26id%3D2&psig=AOvVaw1gFo2WwZqOoJPLDIq5BJDl&ust=1678686478156000&source=images&cd=vfe&ved=0CA0QjRxqFwoTCLCmtc3Y1f0CFQAAAAAdAAAAABAD",
      "open_time": "10.00",
      "close_time": "16.00",
      "location": "165 ถ.บางลี่-หนองวัลย์เปรียง Song Phi Nong, Song Phi Nong District, Suphan Buri 72110",
      "building": "อาคาร4",
      "floor": "3",
      "max_queue_number": "200"
    },
    {
      "id": 4,
      "department_name": "ทันตกรรม",
      "department_image": "https://www.google.com/url?sa=i&url=https%3A%2F%2Fthaksinhospital.com%2Fthaksin%2Fdepartment_detail.php%3Fmenu%3D1%26id%3D2&psig=AOvVaw1gFo2WwZqOoJPLDIq5BJDl&ust=1678686478156000&source=images&cd=vfe&ved=0CA0QjRxqFwoTCLCmtc3Y1f0CFQAAAAAdAAAAABAD",
      "open_time": "10.00",
      "close_time": "16.00",
      "location": "165 ถ.บางลี่-หนองวัลย์เปรียง Song Phi Nong, Song Phi Nong District, Suphan Buri 72110",
      "building": "อาคาร2",
      "floor": "3",
      "max_queue_number": "200"
    }
  ],
  "authorities": [
    {
      "id": "1",
      "first_name": "อถพล",
      "last_name": "สองสี",
      "password": "11111111",
      "authorities_status": "พักงาน",
      "department_id": "1"
    }
  ]
}